LICENSE
s3_objects_tracker/__init__.py
s3_objects_tracker/tracker.py
s3_objects_tracker-0.3.0.dist-info/LICENSE
s3_objects_tracker-0.3.0.dist-info/WHEEL
s3_objects_tracker-0.3.0.dist-info/METADATA
s3_objects_tracker-0.3.0.dist-info/RECORD
