Metadata-Version: 2.1
Name: s3-objects-tracker
Version: 0.3.0
Summary: Track already processed objects inside your s3 bucket.
Home-page: https://github.com/ErhoSen/s3-objects-tracker
License: MIT
Keywords: objects storage,s3,tracker,published objects,published objects tracker
Author: Vladimir Vyazovetskov
Author-email: erhosen@gmail.com
Requires-Python: >=3.9,<4.0
Classifier: Development Status :: 4 - Beta
Classifier: Environment :: Other Environment
Classifier: Framework :: AsyncIO
Classifier: Intended Audience :: Developers
Classifier: License :: OSI Approved :: MIT License
Classifier: Operating System :: OS Independent
Classifier: Programming Language :: Python :: 3
Classifier: Programming Language :: Python :: 3.10
Classifier: Programming Language :: Python :: 3.9
Classifier: Topic :: Software Development :: Libraries :: Python Modules
Classifier: Typing :: Typed
Requires-Dist: aiobotocore (>=2.3.2,<3.0.0)
Project-URL: Repository, https://github.com/ErhoSen/s3-objects-tracker
